{
  "animateLoading": true,
  "bottomRow": 76,
  "capSide": 0,
  "capType": "nc",
  "dividerColor": "#858282",
  "dynamicBindingPathList": [],
  "isLoading": false,
  "isVisible": true,
  "key": "6ujyl8rp07",
  "leftColumn": 3,
  "minWidth": 450,
  "mobileBottomRow": 73,
  "mobileLeftColumn": 3,
  "mobileRightColumn": 23,
  "mobileTopRow": 69,
  "needsErrorInfo": false,
  "orientation": "horizontal",
  "originalBottomRow": 112,
  "originalTopRow": 108,
  "parentColumnSpace": 19.8125,
  "parentId": "0",
  "parentRowSpace": 10,
  "renderMode": "CANVAS",
  "responsiveBehavior": "fill",
  "rightColumn": 59,
  "strokeStyle": "solid",
  "thickness": 2,
  "topRow": 72,
  "type": "DIVIDER_WIDGET",
  "version": 1,
  "widgetId": "kct0ahkw1d",
  "widgetName": "Divider1"
}